banffprocessor/__init__.py
banffprocessor/processor.py
banffprocessor/processor_data.py
banffprocessor/processor_input.py
banffprocessor/exceptions/__init__.py
banffprocessor/metadata/__init__.py
banffprocessor/metadata/metaobjects.py
banffprocessor/metadata/models/__init__.py
banffprocessor/metadata/models/algorithms.py
banffprocessor/metadata/models/donorspecs.py
banffprocessor/metadata/models/editgroups.py
banffprocessor/metadata/models/edits.py
banffprocessor/metadata/models/errorlocspecs.py
banffprocessor/metadata/models/estimators.py
banffprocessor/metadata/models/estimatorspecs.py
banffprocessor/metadata/models/expressions.py
banffprocessor/metadata/models/jobs.py
banffprocessor/metadata/models/massimputationspecs.py
banffprocessor/metadata/models/metadataclass.py
banffprocessor/metadata/models/outlierspecs.py
banffprocessor/metadata/models/processcontrols.py
banffprocessor/metadata/models/processoutputs.py
banffprocessor/metadata/models/proratespecs.py
banffprocessor/metadata/models/uservars.py
banffprocessor/metadata/models/varlists.py
banffprocessor/metadata/models/verifyeditsspecs.py
banffprocessor/metadata/models/weights.py
banffprocessor/nls/__init__.py
banffprocessor/nls/nls.py
banffprocessor/nls/messages/en/LC_MESSAGES/banffprocessor.mo
banffprocessor/nls/messages/fr/LC_MESSAGES/banffprocessor.mo
banffprocessor/procedures/__init__.py
banffprocessor/procedures/factory.py
banffprocessor/procedures/loader.py
banffprocessor/procedures/procedure_interface.py
banffprocessor/procedures/banff_procedures/__init__.py
banffprocessor/procedures/banff_procedures/deterministic.py
banffprocessor/procedures/banff_procedures/donorimputation.py
banffprocessor/procedures/banff_procedures/editstats.py
banffprocessor/procedures/banff_procedures/errorloc.py
banffprocessor/procedures/banff_procedures/estimator.py
banffprocessor/procedures/banff_procedures/job_proc.py
banffprocessor/procedures/banff_procedures/massimputation.py
banffprocessor-2.0.3.dist-info/licenses/LICENSE
banffprocessor-2.0.3.dist-info/METADATA
banffprocessor-2.0.3.dist-info/WHEEL
banffprocessor-2.0.3.dist-info/entry_points.txt
banffprocessor-2.0.3.dist-info/top_level.txt
banffprocessor-2.0.3.dist-info/zip-safe
banffprocessor-2.0.3.dist-info/RECORD
