Metadata-Version: 2.4
Name: banffprocessor
Version: 2.0.3
Summary: The Banff Processor, a tool for creating metadata driven imputation strategies.
Maintainer-email: "Banff Support, Statistics Canada" <statcan.banff-banff.statcan@statcan.gc.ca>
Project-URL: Homepage, https://github.com/StatCan/gensol-banff-processor
Project-URL: Bug Tracker, https://github.com/StatCan/gensol-banff-processor/issues
Classifier: Development Status :: 5 - Production/Stable
Classifier: Programming Language :: Python :: 3
Classifier: License :: OSI Approved :: GNU General Public License v3 or later (GPLv3+)
Classifier: Operating System :: OS Independent
Requires-Python: >=3.10
License-File: LICENSE
Requires-Dist: banff>=3.1.3
Requires-Dist: defusedxml>=0.7.1
Requires-Dist: duckdb<2,>=0.7.0
Requires-Dist: openpyxl>=3.1.2
Requires-Dist: pandas<3,>=2.1.1
Requires-Dist: pyarrow<19,>=14
Requires-Dist: xmlschema>=3.3.1
Provides-Extra: test
Requires-Dist: pytest; extra == "test"
Requires-Dist: pytest-cov; extra == "test"
Requires-Dist: requests; extra == "test"
Requires-Dist: ruff; extra == "test"
Provides-Extra: doc
Requires-Dist: sphinx; extra == "doc"
Requires-Dist: sphinx_rtd_theme; extra == "doc"
Requires-Dist: pydata-sphinx-theme; extra == "doc"
Requires-Dist: myst_parser; extra == "doc"
Dynamic: license-file
